{"cameraMode":{"drawMode":0,"name":"Shaded","section":"Shading Mode"},"sceneLighting":true,"audioPlay":false,"sceneViewState":{"m_AlwaysRefresh":false,"showFog":true,"showSkybox":true,"showFlares":true,"showImageEffects":true,"showParticleSystems":true,"showVisualEffectGraphs":true,"m_FxEnabled":true},"in2DMode":false,"pivot":{"x":-17.163814544677736,"y":3.0,"z":-18.0},"rotation":{"x":-0.012392654083669186,"y":-0.9143543839454651,"z":0.030405815690755845,"w":-0.40464308857917788},"size":1.5406649112701417,"orthographic":false}